svn/__init__.py
svn/common.py
svn/constants.py
svn/local.py
svn/remote.py
svn/utility.py
svn/resources/README.rst
svn/resources/requirements.txt
svn/resources/unicode_test.txt
svn-0.3.44.dist-info/DESCRIPTION.rst
svn-0.3.44.dist-info/METADATA
svn-0.3.44.dist-info/RECORD
svn-0.3.44.dist-info/WHEEL
svn-0.3.44.dist-info/metadata.json
svn-0.3.44.dist-info/top_level.txt
tests/__init__.py
tests/test_common.py
tests/test_remote.py
tests/resources/__init__.py
tests/resources/expected_output.py
