Metadata-Version: 2.0
Name: svn
Version: 0.3.44
Summary: Intuitive Subversion wrapper.
Home-page: https://github.com/dsoprea/PySvn
Author: Dustin Oprea
Author-email: myselfasunder@gmail.com
License: GPL 2
Keywords: svn subversion
Platform: UNKNOWN
Requires-Dist: nose
Requires-Dist: python-dateutil (>=2.2)
